postbracket/bracket.py
postbracket/postfix.py
jy.wb2024-0.0.1.dist-info/METADATA
jy.wb2024-0.0.1.dist-info/WHEEL
jy.wb2024-0.0.1.dist-info/top_level.txt
jy.wb2024-0.0.1.dist-info/RECORD
