Metadata-Version: 2.1
Name: jy.wb2024
Version: 0.0.1
Summary: brackpost
Home-page: https://github.com/Leejo0/jywb.2024-setup
Download-URL: https://github.com/Leejo0/jywb.2024-setup
Author: jy lee
Classifier: Programming Language :: Python :: 3
